simulaqron/__init__.py
simulaqron/network.py
simulaqron/settings.py
simulaqron/sim_util.py
simulaqron/simulaqron.py
simulaqron/.simulaqron_pids/.keep
simulaqron/config/.keep
simulaqron/general/__init__.py
simulaqron/general/errors.py
simulaqron/general/host_config.py
simulaqron/local/__init__.py
simulaqron/local/setup.py
simulaqron/netqasm_backend/__init__.py
simulaqron/netqasm_backend/executioner.py
simulaqron/netqasm_backend/factory.py
simulaqron/netqasm_backend/qnodeos.py
simulaqron/run/__init__.py
simulaqron/run/run.py
simulaqron/sdk/__init__.py
simulaqron/sdk/broadcast_channel.py
simulaqron/sdk/connection.py
simulaqron/sdk/socket.py
simulaqron/start/__init__.py
simulaqron/start/start_qnodeos.py
simulaqron/start/start_vnode.py
simulaqron/toolbox/__init__.py
simulaqron/toolbox/get_simulaqron_path.py
simulaqron/toolbox/has_module.py
simulaqron/toolbox/manage_nodes.py
simulaqron/toolbox/reset.py
simulaqron/toolbox/stabilizer_states.py
simulaqron/virtual_node/__init__.py
simulaqron/virtual_node/basics.py
simulaqron/virtual_node/project_q_simulator.py
simulaqron/virtual_node/quantum.py
simulaqron/virtual_node/qutip_simulator.py
simulaqron/virtual_node/stabilizer_simulator.py
simulaqron/virtual_node/virtual.py
simulaqron-4.0.0.dist-info/LICENSE
simulaqron-4.0.0.dist-info/METADATA
simulaqron-4.0.0.dist-info/WHEEL
simulaqron-4.0.0.dist-info/entry_points.txt
simulaqron-4.0.0.dist-info/top_level.txt
simulaqron-4.0.0.dist-info/RECORD
